music_bg/__init__.py
music_bg/__main__.py
music_bg/argparse.py
music_bg/background.py
music_bg/config.py
music_bg/context.py
music_bg/logging.py
music_bg/utils.py
music_bg/dbus/__init__.py
music_bg/dbus/handlers.py
music_bg/dbus/loop.py
music_bg/img_processors/__init__.py
music_bg/img_processors/blank_img.py
music_bg/img_processors/blur.py
music_bg/img_processors/circle.py
music_bg/img_processors/fit.py
music_bg/img_processors/gradients.py
music_bg/img_processors/load_img.py
music_bg/img_processors/noop.py
music_bg/img_processors/pop.py
music_bg/img_processors/print.py
music_bg/img_processors/processor.py
music_bg/img_processors/resize.py
music_bg/img_variables/__init__.py
music_bg/img_variables/colors.py
music_bg/img_variables/uuid_gen.py
music_bg-0.3.0.dist-info/METADATA
music_bg-0.3.0.dist-info/WHEEL
music_bg-0.3.0.dist-info/entry_points.txt
music_bg-0.3.0.dist-info/licenses/LICENSE
music_bg-0.3.0.dist-info/RECORD
