Metadata-Version: 2.4
Name: music_bg
Version: 0.3.0
Summary: Dynamic wallpapers with power of mpris2.
Project-URL: Homepage, https://github.com/music-bg/music_bg/wiki
Project-URL: Repository, https://github.com/music-bg/music_bg/
Project-URL: Documentation, https://github.com/music-bg/music_bg/wiki
Author-email: Pavel Kirilin <s3riussan@gmail.com>
License-File: LICENSE
Keywords: Dbus,Image Processing,Mpris2,Music,Music Background
Classifier: Operating System :: POSIX :: Linux
Classifier: Topic :: Multimedia :: Sound/Audio
Classifier: Topic :: Scientific/Engineering :: Image Processing
Classifier: Typing :: Typed
Requires-Python: ~=3.11
Requires-Dist: dbus-python<2,>=1.2.16; sys_platform == 'linux'
Requires-Dist: loguru<0.6,>=0.5.3
Requires-Dist: numpy>=2.3.4
Requires-Dist: pillow<13,>=12.0.0
Requires-Dist: pydantic<3,>=2
Requires-Dist: pygobject<4,>=3.40.1; sys_platform == 'linux'
Requires-Dist: requests<3,>=2.26.0
Requires-Dist: scikit-learn>=1.7.2
Requires-Dist: screeninfo>=0.8.1
Requires-Dist: toml>=0.10.2
